LICENSE.md
MANIFEST.in
README.md
requirements.txt
setup.py
pore_c_py/__init__.py
pore_c_py/align_tools.py
pore_c_py/annotate.py
pore_c_py/digest.py
pore_c_py/main.py
pore_c_py/utils.py
pore_c_py/writers.py
pore_c_py.egg-info/PKG-INFO
pore_c_py.egg-info/SOURCES.txt
pore_c_py.egg-info/dependency_links.txt
pore_c_py.egg-info/entry_points.txt
pore_c_py.egg-info/not-zip-safe
pore_c_py.egg-info/requires.txt
pore_c_py.egg-info/top_level.txt
tests/test_align_tools.py
tests/test_annotate.py
tests/test_digest.py
tests/test_utils.py
tests/test_writers.py