Metadata-Version: 2.1
Name: pore-c-py
Version: 2.1.4
Summary: Analyse Pore-C data.
Home-page: https://github.com/epi2me-labs/pore-c-py
Author: epi2melabs
Author-email: epi2melabs@nanoporetech.com
License-File: LICENSE.md
Requires-Dist: biopython==1.79
Requires-Dist: pyarrow==11.0.0
Requires-Dist: pysam==0.20.0
